setup.py
distributions/Binomialdistribution.py
distributions/Gaussiandistribution.py
distributions/Generaldistribution.py
distributions/__init__.py
khachhibhoya_distributions.egg-info/PKG-INFO
khachhibhoya_distributions.egg-info/SOURCES.txt
khachhibhoya_distributions.egg-info/dependency_links.txt
khachhibhoya_distributions.egg-info/not-zip-safe
khachhibhoya_distributions.egg-info/top_level.txt