Metadata-Version: 1.0
Name: khachhibhoya-distributions
Version: 1.1
Summary: Gaussian and binomial distributions
Home-page: UNKNOWN
Author: neha
Author-email: UNKNOWN
License: UNKNOWN
Platform: UNKNOWN
